{"2":{"N":{"E":{"1":0}},"P":{"a":{"c":0},"M":0}," ":{"C":{"h":{"a":{"i":{"n":{"z":0}}}}}},"C":{"e":{"l":{"l":{"o":{"s":0}}}}},"B":{"i":{"C":0}}},"3":{"0":{" ":{"S":{"e":{"c":{"o":{"n":{"d":{"s":{" ":{"t":{"o":{" ":{"M":{"a":{"r":{"s":0}}}}}}}}}}}}}}}},"6":{"0":0}},"4":{"m":{"i":{"n":{"u":{"t":{"e":0}}}}}},"5":{"0":{" ":{"C":{"e":{"n":{"t":0}}}}}," ":{"S":{"e":{"c":{"o":{"n":{"d":{"s":{" ":{"O":{"f":{" ":{"S":{"u":{"m":{"m":{"e":{"r":0}}}}}}}}}}}}}}}}}},"L":{"o":{"r":{"d":{"e":0},"e":{"e":{"n":0}}},"n":{"d":{"o":{"n":{" ":{"G":{"r":{"a":{"m":{"m":{"a":{"r":0}}}}}}}}}}},"s":{" ":{"b":{"u":{"n":{"k":{"e":{"r":{"s":0}}}}}}}}},"a":{"d":{"y":{" ":{"G":{"a":{"g":{"a":0}}},"A":{"n":{"t":{"e":{"b":{"e":{"l":{"l":{"u":{"m":0}}}}}}}}}}}},"n":{"a":{" ":{"D":{"e":{"l":{" ":{"R":{"e":{"y":0}}}}}}}}},"u":{"r":{"a":{" ":{"P":{"a":{"u":{"s":{"i":{"n":{"i":0}}}}}}}}}}," ":{"O":{"r":{"e":{"j":{"a":{" ":{"d":{"e":{" ":{"V":{"a":{"n":{" ":{"G":{"o":{"g":{"h":0}}}}}}}}}}}}}}}},"F":{"o":{"u":{"i":{"n":{"e":0}}}}},"A":{"r":{"r":{"o":{"l":{"l":{"a":{"d":{"o":{"r":{"a":{" ":{"B":{"a":{"n":{"d":{"a":{" ":{"E":{"l":{" ":{"L":{"i":{"m":{"ó":{"n":0}}}}}}}}}}}}}}}}}}}}}}}}}},"t":{"a":{" ":{"M":{"a":{"n":{"g":{"e":{"s":{"h":{"k":{"a":{"r":0}}}}}}}}}}}},"k":{"e":{" ":{"S":{"t":{"r":{"e":{"e":{"t":{" ":{"D":{"i":{"v":{"e":0}}}}}}}}}}}}},"i":{"d":{"b":{"a":{"c":{"k":{" ":{"L":{"u":{"k":{"e":0}}}}}}}}}},"l":{"e":{"h":0}}},"i":{"l":{"y":{" ":{"A":{"l":{"l":{"e":{"n":0}}}}}}," ":{"W":{"a":{"y":{"n":{"e":0}}}}}},"n":{"k":{"i":{"n":{" ":{"P":{"a":{"r":{"k":0}}}}}}},"d":{"s":{"e":{"y":{" ":{"S":{"t":{"i":{"r":{"l":{"i":{"n":{"g":0}}}}}}}}}}}}},"t":{"t":{"l":{"e":{" ":{"M":{"i":{"x":0}}}}}}},"m":{"p":{" ":{"B":{"i":{"z":{"k":{"i":{"t":0}}}}}}}}},"u":{"k":{"e":{" ":{"B":{"r":{"y":{"a":{"n":0}}}}}}},"a":{"n":{" ":{"S":{"a":{"n":{"t":{"a":{"n":{"a":0}}}}}}}}},"p":{"e":{" ":{"F":{"i":{"a":{"s":{"c":{"o":0}}}}}}}},"c":{"a":{"s":{" ":{"L":{"u":{"c":{"c":{"o":0}}}}}}},"i":{"n":{"d":{"a":{" ":{"W":{"i":{"l":{"l":{"i":{"a":{"m":{"s":0}}}}}}}}}}}}},"d":{"a":{"c":{"r":{"i":{"s":0}}}}},"i":{"s":{" ":{"F":{"o":{"n":{"s":{"i":0}}}}}}}},"e":{"d":{" ":{"Z":{"e":{"p":{"p":{"e":{"l":{"i":{"n":0}}}}}}}}},"o":{"n":{"a":{" ":{"L":{"e":{"w":{"i":{"s":0}}}}}}}},"a":{" ":{"M":{"i":{"c":{"h":{"e":{"l":{"e":0}}}}}}}},"i":{"v":{"a":0}},"f":{"t":{" ":{"B":{"o":{"y":0}}}}},"n":{"k":{"a":0}}},"y":{"k":{"k":{"e":{" ":{"L":{"i":0}}}}},"n":{"y":{"r":{"d":{" ":{"S":{"k":{"y":{"n":{"y":{"r":{"d":0}}}}}}}}}}}},"I":{"G":{"A":{"B":{"U":{"E":0}}}}},"M":{"F":{"A":{"O":0}}},"U":{"N":{"A":{" ":{"S":{"E":{"A":0}}}}}},".":{"O":{".":{"C":{".":0}}}},"E":{" ":{"Y":{"O":{"U":{"T":{"H":0}}}}}}},"A":{"v":{"i":{"c":{"i":{"i":0}}},"r":{"i":{"l":{" ":{"L":{"a":{"v":{"i":{"g":{"n":{"e":0}}}}}}}}}},"e":{"n":{"g":{"e":{"d":{" ":{"S":{"e":{"v":{"e":{"n":{"f":{"o":{"l":{"d":0}}}}}}}}}}}},"t":{"u":{"r":{"a":0}}}}}},"r":{"c":{"t":{"i":{"c":{" ":{"M":{"o":{"n":{"k":{"e":{"y":{"s":0}}}}}}}}}},"a":{"d":{"e":{" ":{"F":{"i":{"r":{"e":0}}}}}}},"h":{"i":{"t":{"e":{"c":{"t":{"s":0}}}}}}},"i":{"a":{"n":{"a":{" ":{"G":{"r":{"a":{"n":{"d":{"e":0}}}}}}}}},"j":{"i":{"t":{" ":{"S":{"i":{"n":{"g":{"h":0}}}}}}}}},"m":{"i":{"n":{" ":{"v":{"a":{"n":{" ":{"B":{"u":{"u":{"r":{"e":{"n":0}}}}}}}}}}}}},"a":{"s":{"h":0}}},"d":{"e":{"l":{"e":0," ":{"T":{"a":{"w":{"i":{"l":0}}}}}}},"r":{"i":{"a":{"n":{"o":{" ":{"C":{"e":{"l":{"e":{"n":{"t":{"a":{"n":{"o":0}}}}}}}}}}}}}},"i":{"t":{"y":{"a":{" ":{"N":{"a":{"r":{"a":{"y":{"a":{"n":0}}}}}}}}}}}}," ":{"G":{"r":{"e":{"a":{"t":{" ":{"B":{"i":{"g":{" ":{"W":{"o":{"r":{"l":{"d":0}}}}}}}}}}}}}},"D":{"a":{"y":{" ":{"t":{"o":{" ":{"R":{"e":{"m":{"e":{"m":{"b":{"e":{"r":0}}}}}}}}}}}}}}},"W":{"O":{"L":{"N":{"A":{"T":{"I":{"O":{"N":0}}}}}}}},"l":{"o":{"e":{" ":{"B":{"l":{"a":{"c":{"c":0}}}}}}},"i":{"c":{"i":{"a":{" ":{"K":{"e":{"y":{"s":0}}}}}}},"n":{"e":{" ":{"B":{"a":{"r":{"r":{"o":{"s":0}}}}}}}}},"l":{"i":{"g":{"a":{"t":{"o":{"a":{"h":0}}}}}}},"a":{"n":{" ":{"J":{"a":{"c":{"k":{"s":{"o":{"n":0}}}}}}}}},"e":{"j":{"a":{"n":{"d":{"r":{"o":{" ":{"F":{"e":{"r":{"n":{"á":{"n":{"d":{"e":{"z":0}}}}}}}},"S":{"a":{"n":{"z":0}}}}}}}}}},"s":{"s":{"a":{"n":{"d":{"r":{"a":{" ":{"A":{"m":{"o":{"r":{"o":{"s":{"o":0}}}}}}}}}}}},"o":0}},"x":{" ":{"H":{"e":{"p":{"b":{"u":{"r":{"n":0}}}}}}},"a":{"n":{"d":{"r":{"a":{" ":{"S":{"t":{"a":{"n":0}}}}}}}}}}},"f":{"a":{"a":{"z":0}}},"k":{"i":{"l":{"a":{"d":{"o":{"s":0}}}}}}},"f":{"r":{"o":{"j":{"a":{"c":{"k":0}}}}}},"C":{"/":{"D":{"C":0}}},"m":{"e":{"r":{"i":{"c":{"a":{"n":{" ":{"A":{"u":{"t":{"h":{"o":{"r":{"s":0}}}}}}}}}}}}},"y":{" ":{"W":{"i":{"n":{"e":{"h":{"o":{"u":{"s":{"e":0}}}}}}}}}},"r":{"i":{"n":{"d":{"e":{"r":{" ":{"G":{"i":{"l":{"l":0}}}}}}}}}}},"u":{"s":{"t":{"i":{"n":{" ":{"M":{"a":{"h":{"o":{"n":{"e":0}}}}}}}}}},"g":{"u":{"s":{"t":{" ":{"A":{"l":{"s":{"i":{"n":{"a":0}}}}}}}}}}},"K":{"B":{"4":{"8":0}}},"B":{"B":{"A":0}},"$":{"A":{"P":{" ":{"R":{"o":{"c":{"k":{"y":0}}}}}}}},"n":{"i":{"t":{"t":{"a":0}}},"d":{"r":{"e":{"a":{" ":{"B":{"o":{"c":{"e":{"l":{"l":{"i":0}}}}},"e":{"r":{"g":0}}}}}}},"y":{" ":{"M":{"i":{"n":{"e":{"o":0}}}}}}},"g":{"e":{"l":{" ":{"O":{"l":{"s":{"e":{"n":0}}}}}}}},"a":{" ":{"T":{"i":{"j":{"o":{"u":{"x":0}}}}}}},"u":{"r":{"a":{"d":{"h":{"a":{" ":{"P":{"a":{"u":{"d":{"w":{"a":{"l":0}}}}}}}}}}}}},"t":{"o":{"n":{"i":{"s":{" ":{"R":{"e":{"m":{"o":{"s":0}}}}}},"o":{" ":{"O":{"r":{"o":{"z":{"c":{"o":0}}}}}}}}}}},"n":{"a":{" ":{"V":{"i":{"s":{"s":{"i":0}}}}}}}},".":{"R":{".":{" ":{"R":{"a":{"h":{"m":{"a":{"n":0}}}}}}}}},"L":{"T":{"J":0}},"T":{"B":0},"b":{"e":{"l":{" ":{"P":{"i":{"n":{"t":{"o":{"s":0}}}}}}}},"o":{"v":{"e":{" ":{"&":{" ":{"B":{"e":{"y":{"o":{"n":{"d":0}}}}}}}}}}},"r":{"a":{"h":{"a":{"m":{" ":{"M":{"a":{"t":{"e":{"o":0}}}}}}}}}}},"e":{"r":{"o":{"s":{"m":{"i":{"t":{"h":0}}}}}},"s":{"t":{"h":{"e":{"t":{"i":{"c":{" ":{"P":{"e":{"r":{"f":{"e":{"c":{"t":{"i":{"o":{"n":0}}}}}}}}}}}}}}}}}},"t":{"i":{"f":{" ":{"A":{"s":{"l":{"a":{"m":0}}}}}}}},"g":{"a":{"i":{"n":{"s":{"t":{" ":{"M":{"e":{"!":0}}}}}}},"p":{"o":{"r":{"n":{"i":{"s":0}}}}}},"n":{"e":{"s":{" ":{"O":{"b":{"e":{"l":0}}}}}}}},"k":{"o":{"n":0}},"h":{"z":{"e":{"e":0}}},"p":{"i":{"n":{"k":0}}},"A":{"A":0},"O":{"A":0},"s":{" ":{"A":{"n":{"i":{"m":{"a":{"l":{"s":0}}}}}}},"a":{"f":{" ":{"A":{"v":{"i":{"d":{"a":{"n":{" ":{"&":{" ":{"t":{"h":{"e":{" ":{"M":{"o":{"j":{"o":{"s":0}}}}}}}}}}}}}}}}}}}},"h":{"a":{" ":{"B":{"h":{"o":{"s":{"l":{"e":0}}}}}}}},"g":{"e":{"i":{"r":0}}}},"S":{"A":{"P":{" ":{"F":{"e":{"r":{"g":0}}}}}}},"z":{"e":{"a":{"l":{"i":{"a":{" ":{"B":{"a":{"n":{"k":{"s":0}}}}}}}}}}},"i":{"k":{"o":0}}},"K":{"a":{"t":{"y":{" ":{"P":{"e":{"r":{"r":{"y":0}}}},"B":0}}},"n":{"y":{"e":{" ":{"W":{"e":{"s":{"t":0}}}}}}},"c":{"e":{"y":{" ":{"M":{"u":{"s":{"g":{"r":{"a":{"v":{"e":{"s":0}}}}}}}}}}}},"i":{"s":{"e":{"r":{" ":{"C":{"h":{"i":{"e":{"f":{"s":0}}}}}}}}}},"v":{"i":{"n":{"s":{"k":{"y":0}}},"t":{"a":{" ":{"K":{"r":{"i":{"s":{"h":{"n":{"a":{"m":{"u":{"r":{"t":{"h":{"y":0}}}}}}}}}}}}}}}}},"r":{"m":{"i":{"n":0}},"u":{"n":{"e":{"s":{"h":0}}}}}},"i":{"d":{" ":{"I":{"n":{"k":0}},"C":{"u":{"d":{"i":0}}}},"z":{" ":{"B":{"o":{"p":{" ":{"K":{"i":{"d":{"s":0}}}}}}}}}},"n":{"g":{"s":{" ":{"o":{"f":{" ":{"L":{"e":{"o":{"n":0}}}}}}}}}},"m":{" ":{"C":{"e":{"s":{"a":{"r":{"i":{"o":{"n":0}}}}}}}}},"s":{"h":{"o":{"r":{"e":{" ":{"K":{"u":{"m":{"a":{"r":0}}}}}}}}},"-":{"M":{"y":{"-":{"F":{"t":{"2":0}}}}}}}},"l":{"i":{"n":{"g":{"a":{"n":{"d":{"e":0}}}}}},"a":{"n":{"g":{"k":{"a":{"r":{"u":{"s":{"s":{"e":{"l":{"l":0}}}}}}}}}}}},"e":{"n":{"d":{"r":{"i":{"c":{"k":{" ":{"L":{"a":{"m":{"a":{"r":0}}}}}}}}}}},"i":{"t":{"h":{" ":{"U":{"r":{"b":{"a":{"n":0}}}}}}}},"l":{"l":{"y":{" ":{"C":{"l":{"a":{"r":{"k":{"s":{"o":{"n":0}}}}}}}}}},"i":{"s":0}},"$":{"h":{"a":0}},"a":{"n":{"e":0}},"y":{"s":{" ":{"N":{" ":{"K":{"r":{"a":{"t":{"e":{"s":0}}}}}}}}}}},"y":{"l":{"i":{"e":{" ":{"M":{"i":{"n":{"o":{"g":{"u":{"e":0}}}}}}}}}},"g":{"o":0}},"r":{"i":{"s":{"t":{"e":{"n":{" ":{"B":{"e":{"l":{"l":0}}}}}}}}},"e":{"w":{"e":{"l":{"l":{"a":0}}}}}},"o":{"d":{"a":{"l":{"i":{"n":{"e":0}}}}},"r":{"n":0},"l":{"l":{"e":{"g":{"a":{"h":0}}}}}},".":{"w":{"i":{"l":{"l":0}}}," ":{"M":{"i":{"c":{"h":{"e":{"l":{"l":{"e":0}}}}}}}}},"R":{"E":{"V":{"A":0}}},"A":{"N":{"A":{"-":{"B":{"O":{"O":{"N":0}}}}}},"Y":{"T":{"R":{"A":{"N":{"A":{"D":{"A":0}}}}}}}}},"B":{"1":{"A":{"4":0}},"e":{"y":{"o":{"n":{"c":{"é":0}}}},"c":{"k":0},"h":{"e":{"m":{"o":{"t":{"h":0}}}}},"e":{" ":{"G":{"e":{"e":{"s":0}}}}},"a":{"t":{"r":{"i":{"c":{"e":{" ":{"E":{"g":{"l":{"i":0}}}}}}}}}}},"r":{"u":{"n":{"o":{" ":{"M":{"a":{"r":{"s":0}}}},"r":{"i":{" ":{"s":{"a":{"s":0}}}}}}},"c":{"e":{" ":{"S":{"p":{"r":{"i":{"n":{"g":{"s":{"t":{"e":{"e":{"n":0}}}}}}}}}}}}}},"i":{"t":{"n":{"e":{"y":{" ":{"S":{"p":{"e":{"a":{"r":{"s":0}}}}}}}}}},"n":{"g":{" ":{"M":{"e":{" ":{"t":{"h":{"e":{" ":{"H":{"o":{"r":{"i":{"z":{"o":{"n":0}}}}}}}}}}}}}}}}},"o":{"k":{"e":{"n":{" ":{"B":{"e":{"l":{"l":{"s":0}}}}}}}},"i":{"l":{"e":{"r":{"s":0}}}},"o":{"d":{"s":0},"k":{"s":{" ":{"&":{" ":{"D":{"u":{"n":{"n":0}}}}}}}}}},"a":{"n":{"t":{"l":{"e":{"y":{" ":{"G":{"i":{"l":{"b":{"e":{"r":{"t":0}}}}}}}}}}}},"d":{" ":{"P":{"a":{"i":{"s":{"l":{"e":{"y":0}}}}}}}}},"e":{"t":{"t":{" ":{"E":{"l":{"d":{"r":{"e":{"d":{"g":{"e":0}}}}}}}}}}}},"a":{"s":{"t":{"i":{"l":{"l":{"e":0}}}}},"n":{"d":{" ":{"o":{"f":{" ":{"H":{"o":{"r":{"s":{"e":{"s":0}}}}}}}}},"a":{" ":{"S":{"i":{"n":{"a":{"l":{"o":{"e":{"n":{"s":{"e":{" ":{"M":{"S":{" ":{"d":{"e":{" ":{"S":{"e":{"r":{"g":{"i":{"o":{" ":{"L":{"i":{"z":{"á":{"r":{"r":{"a":{"g":{"a":0}}}}}}}}}}}}}}}}}}}}}}}}}}}}}}}},"E":{"l":{" ":{"R":{"e":{"c":{"o":{"d":{"o":{" ":{"D":{"e":{" ":{"C":{"r":{"u":{"z":{" ":{"L":{"i":{"z":{"á":{"r":{"r":{"a":{"g":{"a":0}}}}}}}}}}}}}}}}}}}}}}}}}},"L":{"o":{"s":{" ":{"R":{"e":{"c":{"o":{"d":{"i":{"t":{"o":{"s":0}}}}}}}}}}}},"C":{"a":{"r":{"n":{"a":{"v":{"a":{"l":0}}}}}}},"R":{"a":{"n":{"c":{"h":{"o":{" ":{"V":{"i":{"e":{"j":{"o":0}}}}}}}}}}}}}},"k":{"s":0}},"k":{"e":{"r":{"m":{"a":{"t":0}}}}},"b":{"y":{"s":{"h":{"a":{"m":{"b":{"l":{"e":{"s":0}}}}}}}}}},"o":{"m":{"b":{"a":{"y":{" ":{"B":{"i":{"c":{"y":{"c":{"l":{"e":{" ":{"C":{"l":{"u":{"b":0}}}}}}}}}}}}}}}},"b":{" ":{"M":{"a":{"r":{"l":{"e":{"y":0}}}}},"D":{"y":{"l":{"a":{"n":0}}}},"S":{"i":{"n":{"c":{"l":{"a":{"r":0}}}}}}}},"n":{" ":{"I":{"v":{"e":{"r":0}}},"J":{"o":{"v":{"i":0}}}},"d":{"a":{"x":0}}},"y":{"z":{"o":{"n":{"e":0}}}," ":{"&":{" ":{"B":{"e":{"a":{"r":0}}}}},"G":{"e":{"o":{"r":{"g":{"e":0}}}}}}},"o":{"k":{"a":{" ":{"S":{"h":{"a":{"d":{"e":0}}}}}}}},"d":{"y":{"b":{"a":{"n":{"g":{"e":{"r":{"s":0}}}}}}}},"s":{"s":{"e":0}}},"i":{"r":{"d":{"y":0}},"g":{"B":{"a":{"n":{"g":0}}}," ":{"S":{"e":{"a":{"n":0}}},"D":{"a":{"d":{"d":{"y":{" ":{"W":{"e":{"a":{"v":{"e":0}}}}}}}}}}}},"l":{"a":{"l":{" ":{"S":{"a":{"e":{"e":{"d":0}}}}}}}}},"l":{"a":{"k":{"e":{" ":{"S":{"h":{"e":{"l":{"t":{"o":{"n":0}}}}}}}}},"c":{"k":{" ":{"S":{"a":{"b":{"b":{"a":{"t":{"h":0}}}}}}}}},"s":{"t":{"e":{"r":{"J":{"a":{"x":{"x":0}}}}}}}},"i":{"s":{"s":{" ":{"n":{" ":{"E":{"s":{"o":0}}}}}}}},"u":{"r":0}},"u":{"s":{"t":{"a":{" ":{"R":{"h":{"y":{"m":{"e":{"s":0}}}}}}}},"h":{"i":{"d":{"o":0}}}},"n":{"b":{"u":{"r":{"y":0}}}}},".":{"o":{".":{"B":0}}},"A":{"P":0,"B":{"Y":{"M":{"E":{"T":{"A":{"L":0}}}}}}},"U":{"M":{"P":{" ":{"O":{"F":{" ":{"C":{"H":{"I":{"C":{"K":{"E":{"N":0}}}}}}}}}}}}}},"M":{"8":{"3":0},"i":{"l":{"e":{"y":{" ":{"C":{"y":{"r":{"u":{"s":0}}}}}}},"k":{"y":{" ":{"C":{"h":{"a":{"n":{"c":{"e":0}}}}}}}}},"k":{"e":{" ":{"W":{"i":{"l":{"l":{" ":{"M":{"a":{"d":{"e":{"-":{"I":{"t":0}}}}}}}}}}},"C":{"a":{"n":{"d":{"y":{"s":0}}}}},"P":{"o":{"s":{"n":{"e":{"r":0}}}}}}},"a":{"$":0," ":{"S":{"i":{"n":{"g":{"h":0}}}}}}},"c":{"h":{"a":{"e":{"l":{" ":{"J":{"a":{"c":{"k":{"s":{"o":{"n":0}}}}}},"B":{"u":{"b":{"l":{"é":0}}}}}}}},"e":{"l":{" ":{"T":{"e":{"l":{"ó":0}}}},"e":{" ":{"B":{"r":{"a":{"v":{"i":0}}}}}}}}}},"g":{"u":{"e":{"l":0}},"o":{"s":0}},"s":{"t":{"e":{"r":{" ":{"Y":{"o":{"u":0}}}}}}},"n":{"d":{" ":{"V":{"o":{"r":{"t":{"e":{"x":0}}}}}}}},"r":{"a":{"n":{"d":{"a":{" ":{"L":{"a":{"m":{"b":{"e":{"r":{"t":0}}}}}}}}}}}},"a":{" ":{"M":{"a":{"r":{"t":{"i":{"n":{"a":0}}}}}}}}},"a":{"c":{"k":{"l":{"e":{"m":{"o":{"r":{"e":{" ":{"&":{" ":{"R":{"y":{"a":{"n":{" ":{"L":{"e":{"w":{"i":{"s":0}}}}}}}}}}}}}}}}}}}," ":{"M":{"i":{"l":{"l":{"e":{"r":0}}}}}}},"r":{"t":{"i":{"n":{" ":{"G":{"a":{"r":{"r":{"i":{"x":0}}}}},"S":{"o":{"l":{"v":{"e":{"i":{"g":0}}}}}}},"a":{" ":{"S":{"t":{"o":{"e":{"s":{"s":{"e":{"l":0}}}}}}}}}}},"e":{"r":{"i":{"a":0}}}},"c":{" ":{"A":{"n":{"t":{"h":{"o":{"n":{"y":0}}}}}}},"o":{" ":{"M":{"e":{"n":{"g":{"o":{"n":{"i":0}}}}}},"B":{"o":{"r":{"s":{"a":{"t":{"o":0}}}}}}}},"e":{"l":{"o":{" ":{"J":{"e":{"n":{"e":{"c":{"i":0}}}}}}}}}},"i":{"a":{"h":{" ":{"C":{"a":{"r":{"e":{"y":0}}}}}}},"l":{"y":{"n":{" ":{"M":{"a":{"n":{"s":{"o":{"n":0}}}}}}}}},"n":{"a":{" ":{"a":{"n":{"d":{" ":{"T":{"h":{"e":{" ":{"D":{"i":{"a":{"m":{"o":{"n":{"d":{"s":0}}}}}}}}}}}}}}}}}}},"o":{"o":{"n":{" ":{"5":0}}}}},"i":{"t":{"r":{"e":{" ":{"G":{"i":{"m":{"'":{"s":0}}}}}}}}},"j":{"o":{"r":{" ":{"L":{"a":{"z":{"e":{"r":0}}}}}}}},"d":{"o":{"n":{"n":{"a":0}}}},"l":{"ú":0,"u":{"m":{"a":0}}},"x":{"ï":{"m":{"o":{" ":{"P":{"a":{"r":{"k":0}}}}}}}," ":{"P":{"e":{"z":{"z":{"a":{"l":{"i":0}}}}}},"H":{"e":{"r":{"r":{"e":0}}}}}},"n":{"u":{"e":{"l":{" ":{"C":{"a":{"r":{"r":{"a":{"s":{"c":{"o":0}}}}}}}}}}},"d":{"i":{"s":{"a":0}}},"n":{"a":{" ":{"D":{"e":{"y":0}}}}}},"s":{"s":{"i":{"v":{"e":{" ":{"A":{"t":{"t":{"a":{"c":{"k":0}}}}}}}}}}},"y":{"'":{"n":0},"a":{" ":{"J":{"a":{"n":{"e":{" ":{"C":{"o":{"l":{"e":{"s":0}}}}}}}}}}}},"t":{"t":{" ":{"R":{"e":{"d":{"m":{"a":{"n":0}}}}},"C":{"o":{"r":{"b":{"y":0}}}}}}},"g":{"i":{"c":0}}},"e":{"t":{"a":{"l":{"l":{"i":{"c":{"a":0}}}}},"r":{"o":{"n":{"o":{"m":{"y":0}}}},"i":{"c":0}}},"r":{"c":{"y":{"M":{"e":0}}}},"l":{"e":{"n":{"d":{"i":0}}}},"d":{"i":{"n":{"a":0}}}},"u":{"m":{"f":{"o":{"r":{"d":{" ":{"a":{"n":{"d":{" ":{"S":{"o":{"n":{"s":0}}}}}}}}}}}}},"s":{"e":0}},"o":{"g":{"w":{"a":{"i":0}}},"h":{"i":{"t":{" ":{"C":{"h":{"a":{"u":{"h":{"a":{"n":0}}}}}}}}},"a":{"m":{"m":{"e":{"d":{" ":{"R":{"a":{"f":{"i":0}}}}}}}}}},"b":{"y":0},"d":{"à":0,"e":{"s":{"t":{" ":{"M":{"o":{"u":{"s":{"e":0}}}}}}},"r":{"a":{"t":0}}}},"u":{"n":{"t":{" ":{"K":{"i":{"m":{"b":{"i":{"e":0}}}}}}}}}},"K":{"T":{"O":0}},"r":{".":{" ":{"P":{"r":{"o":{"b":{"z":0}}}}}}},"G":{"M":{"T":0}},"y":{" ":{"C":{"h":{"e":{"m":{"i":{"c":{"a":{"l":{" ":{"R":{"o":{"m":{"a":{"n":{"c":{"e":0}}}}}}}}}}}}}}}}},".":{"I":{".":{"A":{".":0}}}},"I":{"S":{"I":{"A":0}}},"s":{" ":{"M":{"r":0}}},"A":{"N":{" ":{"W":{"I":{"T":{"H":{" ":{"A":{" ":{"M":{"I":{"S":{"S":{"I":{"O":{"N":0}}}}}}}}}}}}}}}},"ö":{"t":{"l":{"e":{"y":{" ":{"C":{"r":{"ü":{"e":0}}}}}}}}}},"I":{"m":{"a":{"g":{"i":{"n":{"e":{" ":{"D":{"r":{"a":{"g":{"o":{"n":{"s":0}}}}}}}}}}},"n":{"y":0}}},"d":{"i":{"n":{"a":{" ":{"M":{"e":{"n":{"z":{"e":{"l":0}}}}}}}}}},"c":{"o":{"n":{"a":{" ":{"P":{"o":{"p":0}}}}}},"e":{"d":{" ":{"E":{"a":{"r":{"t":{"h":0}}}}}}," ":{"C":{"u":{"b":{"e":0}}}}}},"n":{"d":{"i":{"l":{"a":0}}},"n":{"a":0},"g":{"r":{"i":{"d":{" ":{"M":{"i":{"c":{"h":{"a":{"e":{"l":{"s":{"o":{"n":0}}}}}}}}}}}}}}},"U":0,"v":{"e":{"t":{"e":{" ":{"S":{"a":{"n":{"g":{"a":{"l":{"o":0}}}}}}}}}},"o":{" ":{"M":{"o":{"z":{"a":{"r":{"t":0}}}}}}}},"N":{"X":{"S":0}},"r":{"o":{"n":{" ":{"M":{"a":{"i":{"d":{"e":{"n":0}}}}}}}},"i":{"e":{" ":{"R":{"é":{"v":{"o":{"l":{"t":{"é":{"s":0}}}}}}}}}}},"l":{"l":{"y":0}," ":{"D":{"i":{"v":{"o":0}}}}}},"E":{"m":{"i":{"n":{"e":{"m":{"$":0," ":{"f":{"e":{"a":{"t":{" ":{"R":{"i":{"h":{"a":{"n":{"n":{"a":0}}}}}}}}}}}}}}},"s":{" ":{"K":{"i":{"l":{"l":{"a":0}}}}}}},"p":{"i":{"r":{"e":{" ":{"o":{"f":{" ":{"t":{"h":{"e":{" ":{"S":{"u":{"n":0}}}}}}}}}}}}}},"e":{"l":{"i":{" ":{"S":{"a":{"n":{"d":{"e":0}}}}}}}},"m":{"a":{"$":0," ":{"M":{"a":{"r":{"r":{"o":{"n":{"e":0}}}}}}},"n":{"u":{"e":{"l":{" ":{"M":{"o":{"i":{"r":{"e":0}}}}}}}}}}}},"l":{"l":{"i":{"e":{" ":{"G":{"o":{"u":{"l":{"d":{"i":{"n":{"g":0}}}}}}}}}}},"i":{"s":{"a":0}," ":{"Y":{"o":{"u":{"n":{"g":{" ":{"B":{"a":{"n":{"d":0}}}}}}}}}}},"y":{"a":{"r":{" ":{"F":{"o":{"x":0}}}}}},"t":{"o":{"n":{" ":{"J":{"o":{"h":{"n":0}}}}}}},"b":{"o":{"w":0}},"e":{"n":{" ":{"L":{"e":{"v":{"o":{"n":0}}}}}},"c":{"t":{"r":{"i":{"c":{" ":{"L":{"i":{"g":{"h":{"t":{" ":{"O":{"r":{"c":{"h":{"e":{"s":{"t":{"r":{"a":0}}}}}}}}}}}}}}}}}}}}}," ":{"T":{"r":{"o":{"n":{"o":{" ":{"d":{"e":{" ":{"M":{"e":{"x":{"i":{"c":{"o":0}}}}}}}}}}}}}}},"v":{"i":{"s":{" ":{"C":{"o":{"s":{"t":{"e":{"l":{"l":{"o":0}}}}}}}}}}}},"d":{" ":{"S":{"h":{"e":{"e":{"r":{"a":{"n":0}}}}}}},"i":{"t":{"o":{"r":{"s":0}}}},"u":{"a":{"r":{"d":{"o":{" ":{"C":{"o":{"s":{"t":{"a":0}}}}}}}}}},"w":{"a":{"r":{"d":{" ":{"S":{"h":{"a":{"r":{"p":{"e":{" ":{"&":{" ":{"t":{"h":{"e":{" ":{"M":{"a":{"g":{"n":{"e":{"t":{"i":{"c":{" ":{"Z":{"e":{"r":{"o":{"s":0}}}}}}}}}}}}}}}}}}}}}}}}}}}}}}}},"n":{"r":{"i":{"q":{"u":{"e":{" ":{"I":{"g":{"l":{"e":{"s":{"i":{"a":{"s":0}}}}}}}}}}}}}},"x":{"o":0,"t":{"r":{"e":{"m":{"o":{"d":{"u":{"r":{"o":0}}}}}}}}},"r":{"i":{"c":{" ":{"C":{"h":{"u":{"r":{"c":{"h":0}}}},"l":{"a":{"p":{"t":{"o":{"n":0}}}}}},"P":{"a":{"s":{"l":{"a":{"y":0}}}}}}}},"o":{"s":{" ":{"R":{"a":{"m":{"a":{"z":{"z":{"o":{"t":{"t":{"i":0}}}}}}}}}}}},"a":{"s":{"u":{"r":{"e":0}}}}},"v":{"a":{"n":{"e":{"s":{"c":{"e":{"n":{"c":{"e":0}}}}}}}}},"a":{"g":{"l":{"e":{"s":0}}}},"X":{"I":{"L":{"E":0}},"O":{"-":{"M":0,"K":0}}},"s":{"t":{"o":{"p":{"a":0}}},"p":{"i":{"n":{"o":{"z":{"a":{" ":{"P":{"a":{"z":0}}}}}}}}},"k":{"i":{"m":{"o":{" ":{"C":{"a":{"l":{"l":{"b":{"o":{"y":0}}}}}}}}}}}},"-":{"4":{"0":0},"G":{"i":{"r":{"l":{"s":0}}}}}},"P":{"i":{"t":{"b":{"u":{"l":{"l":0}}}},"n":{"k":{" ":{"F":{"l":{"o":{"y":{"d":0}}}}}}},"x":{"i":{"e":{"s":0}}},"e":{"r":{"c":{"e":{" ":{"t":{"h":{"e":{" ":{"V":{"e":{"i":{"l":0}}}}}}}}}}}}},"h":{"a":{"r":{"r":{"e":{"l":{"l":0}}}}},"o":{"e":{"n":{"i":{"x":0}}}},"i":{"l":{" ":{"C":{"o":{"l":{"l":{"i":{"n":{"s":0}}}}}}},"l":{"i":{"p":{" ":{"P":{"h":{"i":{"l":{"l":{"i":{"p":{"s":0}}}}}}}}}}}}}},"a":{"s":{"s":{"e":{"n":{"g":{"e":{"r":0}}}},"i":{"o":{"n":{" ":{"P":{"i":{"t":0}}}}}}}},"r":{"a":{"m":{"o":{"r":{"e":0}}}}},"n":{"i":{"c":{"!":{" ":{"A":{"t":{" ":{"t":{"h":{"e":{" ":{"D":{"i":{"s":{"c":{"o":0}}}}}}}}}}}}}}}},"u":{"l":{" ":{"M":{"c":{"C":{"a":{"r":{"t":{"n":{"e":{"y":0}}}}}}}}},"a":{" ":{"F":{"e":{"r":{"n":{"a":{"n":{"d":{"e":{"s":0}}}}}}}}}}}},"b":{"l":{"o":{" ":{"A":{"l":{"b":{"o":{"r":{"a":{"n":0}}}}}}}}}},"t":{" ":{"M":{"e":{"t":{"h":{"e":{"n":{"y":0}}}}}}}},"p":{"o":{"n":0}},"l":{"o":{"m":{"a":{" ":{"F":{"a":{"i":{"t":{"h":0}}}}}}}}},"o":{"l":{"o":{" ":{"N":{"u":{"t":{"i":{"n":{"i":0}}}}}}}}}},"!":{"n":{"k":0}},"r":{"i":{"n":{"c":{"e":{" ":{"R":{"o":{"y":{"c":{"e":0}}}}}}}},"t":{"a":{"m":0}},"y":{"a":{"n":{"k":{"a":{" ":{"C":{"h":{"o":{"p":{"r":{"a":0}}}}}}}}}}}}},"e":{"a":{"r":{"l":{" ":{"J":{"a":{"m":0}}}}}},"r":{"f":{"u":{"m":{"e":0}}},"i":{"p":{"h":{"e":{"r":{"y":0}}}}}},"n":{"t":{"a":{"t":{"o":{"n":{"i":{"x":0}}}}}}},"t":{"e":{"r":{" ":{"M":{"a":{"f":{"f":{"a":{"y":0}}}}}}}," ":{"S":{"e":{"e":{"g":{"e":{"r":0}}}}}}}," ":{"S":{"h":{"o":{"p":{" ":{"B":{"o":{"y":{"s":0}}}}}}}}}}},"H":{"A":{"N":{"T":{"O":{"G":{"R":{"A":{"M":0}}}}}}}},"s":{"y":0},"l":{"a":{"n":{" ":{"B":0}},"c":{"e":{"b":{"o":0}}}},"u":{"m":{"b":0}}},"é":{"r":{"i":{"c":{"l":{"e":{"s":0}}}}}},"o":{"r":{"t":{"u":{"g":{"a":{"l":{".":{" ":{"T":{"h":{"e":{" ":{"M":{"a":{"n":0}}}}}}}}}}}}}}},"I":{"N":{"K":0}}},"D":{"a":{"f":{"t":{" ":{"P":{"u":{"n":{"k":{"$":0," ":{"f":{"e":{"a":{"t":{" ":{"P":{"h":{"a":{"r":{"r":{"e":{"l":{"l":{" ":{"W":{"i":{"l":{"l":{"i":{"a":{"m":{"s":0}}}}}}}}}}}}}}}}}}}}}}}}}}}}},"v":{"i":{"d":{" ":{"G":{"u":{"e":{"t":{"t":{"a":0}}}}},"B":{"i":{"s":{"b":{"a":{"l":0}}}},"o":{"w":{"i":{"e":0}}}},"N":{"a":{"i":{"l":0}}},"D":{"a":{"l":{"l":{"a":{"s":0}}}}}}}},"e":{" ":{"K":{"o":{"z":0}}}}},"d":{"d":{"y":{" ":{"Y":{"a":{"n":{"k":{"e":{"e":0}}}}}}}}},"u":{"g":{"h":{"t":{"r":{"y":0},"e":{"r":0}}}}},"n":{"i":{" ":{"M":{"a":{"r":{"t":{"í":{"n":0}}}}}},"e":{"l":{"l":{"e":{" ":{"B":{"r":{"a":{"d":{"b":{"e":{"r":{"y":0}}}}}}}}}},"e":{" ":{"S":{"i":{"l":{"v":{"e":{"s":{"t":{"r":{"i":0}}}}}}}}}}," ":{"B":{"a":{"r":{"e":{"n":{"b":{"o":{"i":{"m":0}}}}}}}}}}}},"n":{"y":{" ":{"B":{"r":{"o":{"w":{"n":0}}}}}}}},"r":{"i":{"u":{"s":{" ":{"R":{"u":{"c":{"k":{"e":{"r":0}}}}}}}}}},"p":{"p":{"y":0}},"l":{"★":{"s":{"h":{"a":{"b":{"e":{"t":0}}}}}}},"m":{"i":{"e":{"n":{" ":{"J":{"u":{"r":{"a":{"d":{"o":0}}}}}}}}}}},"r":{"a":{"k":{"e":0}},".":{" ":{"D":{"r":{"e":0}}}},"e":{"a":{"m":{" ":{"T":{"h":{"e":{"a":{"t":{"e":{"r":0}}}}}}}}}}},"e":{"m":{"i":{" ":{"L":{"o":{"v":{"a":{"t":{"o":0}}}}}}}},"p":{"e":{"c":{"h":{"e":{" ":{"M":{"o":{"d":{"e":0}}}}}}}}},"o":{"r":{"r":{"o":0}}},"f":{" ":{"L":{"e":{"p":{"p":{"a":{"r":{"d":0}}}}}}}},"e":{"p":{" ":{"P":{"u":{"r":{"p":{"l":{"e":0}}}}}}}},"a":{"t":{"h":{" ":{"C":{"a":{"b":{" ":{"f":{"o":{"r":{" ":{"C":{"u":{"t":{"i":{"e":0}}}}}}}}}}}}}}}},"n":{"t":{"e":0}}},"i":{"s":{"c":{"l":{"o":{"s":{"u":{"r":{"e":0}}}}}}},"m":{"i":{"t":{"r":{"i":{" ":{"V":{"e":{"g":{"a":{"s":0}}}}}}}}}},"e":{"r":{"k":{"s":{" ":{"B":{"e":{"n":{"t":{"l":{"e":{"y":0}}}}}}}}}}," ":{"T":{"o":{"t":{"e":{"n":{" ":{"H":{"o":{"s":{"e":{"n":0}}}}}}}}}}}},"l":{"l":{"o":{"n":{" ":{"F":{"r":{"a":{"n":{"c":{"i":{"s":0}}}}}}}}}}},"x":{"i":{"e":{" ":{"C":{"h":{"i":{"c":{"k":{"s":0}}}}}}}}},"r":{" ":{"e":{"n":{" ":{"g":{"r":{"e":{"y":0}}}}}}}},"p":{"l":{"o":0}},"z":{"z":{"e":{"e":{" ":{"R":{"a":{"s":{"c":{"a":{"l":0}}}}}}}}}}},"v":{"b":{"b":{"s":0}}},"J":{" ":{"F":{"r":{"e":{"s":{"h":0}}}},"A":{"n":{"t":{"o":{"i":{"n":{"e":0}}}}}},"K":{"h":{"a":{"l":{"e":{"d":0}}}}},"S":{"n":{"a":{"k":{"e":0}}}},"B":{"l":{"3":{"n":{"d":0}}}}}},"o":{"l":{"l":{"y":{" ":{"P":{"a":{"r":{"t":{"o":{"n":0}}}}}}}}},"n":{" ":{"O":{"m":{"a":{"r":0}}}},"n":{"a":{" ":{"S":{"u":{"m":{"m":{"e":{"r":0}}}}}}}}}},"V":{"B":{"B":{"S":{" ":{"&":{" ":{"B":{"o":{"r":{"g":{"e":{"o":{"u":{"s":0}}}}}}}}}}}}}},"u":{"m":{" ":{"D":{"u":{"m":{" ":{"G":{"i":{"r":{"l":{"s":0}}}}}}}}}},"k":{"e":{" ":{"D":{"u":{"m":{"o":{"n":{"t":0}}}}}}}},"l":{"c":{"e":{" ":{"M":{"a":{"r":{"í":{"a":0}}}}}}}},"c":{"k":{" ":{"S":{"a":{"u":{"c":{"e":0}}}}}}}},"R":{"E":{"A":{"M":{"S":{" ":{"C":{"O":{"M":{"E":{" ":{"T":{"R":{"U":{"E":0}}}}}}}}}}}}}}},"O":{"n":{"e":{"R":{"e":{"p":{"u":{"b":{"l":{"i":{"c":0}}}}}}}," ":{"D":{"i":{"r":{"e":{"c":{"t":{"i":{"o":{"n":0}}}}}}}}}}},"l":{"l":{"y":{" ":{"M":{"u":{"r":{"s":0}}}}}},"a":0,"i":{"v":{"e":{"r":{" ":{"H":{"e":{"l":{"d":{"e":{"n":{"s":0}}}}}}}}}}}},"f":{" ":{"M":{"o":{"n":{"s":{"t":{"e":{"r":{"s":{" ":{"a":{"n":{"d":{" ":{"M":{"e":{"n":0}}}}}}}}}}}}}},"i":{"c":{"e":{" ":{"&":{" ":{"M":{"e":{"n":0}}}}}}}}}}},"a":{"s":{"i":{"s":0}}},"u":{"t":{"K":{"a":{"s":{"t":0}}}}}," ":{"R":{"a":{"p":{"p":{"a":0}}}}},"z":{"a":{"r":{"k":{" ":{"H":{"e":{"n":{"r":{"y":0}}}}}}}}},"d":{"e":{"s":{"z":{"a":0}}}}},"S":{"h":{"a":{"k":{"i":{"r":{"a":0}},"a":{" ":{"P":{"o":{"n":{"k":0}}},"L":{"o":{"v":{"e":{"l":{"e":{"s":{"s":0}}}}}}}}}},"n":{"k":{"a":{"r":{" ":{"M":{"a":{"h":{"a":{"d":{"e":{"v":{"a":{"n":0}}}}}}}}},"-":{"E":{"h":{"s":{"a":{"a":{"n":{"-":{"L":{"o":{"y":0}}}}}}}}}}}}},"i":{"a":{" ":{"T":{"w":{"a":{"i":{"n":0}}}}}}}},"a":{"n":0},"r":{"o":{"n":{" ":{"J":{"o":{"n":{"e":{"s":{" ":{"a":{"n":{"d":{" ":{"t":{"h":{"e":{" ":{"D":{"a":{"p":{"-":{"K":{"i":{"n":{"g":{"s":0}}}}}}}}}}}}}}}}}}}}}}}}}}},"o":{"w":{"t":{"e":{"k":0}}}},"r":{"e":{"y":{"a":{" ":{"G":{"h":{"o":{"s":{"h":{"a":{"l":0}}}}}}}}}}},"e":{"r":{"y":{"l":{" ":{"C":{"r":{"o":{"w":0}}}}}}}}},"t":{"r":{"o":{"m":{"a":{"e":0}}}},"e":{"v":{"e":{" ":{"A":{"o":{"k":{"i":0}}}}}}},".":{" ":{"V":{"i":{"n":{"c":{"e":{"n":{"t":0}}}}}},"L":{"u":{"c":{"i":{"a":0}}}}}},"o":{"r":{"m":{" ":{"Q":{"u":{"e":{"e":{"n":0}}}}}}}},"a":{"m":{"1":{"n":{"a":0}}}},"i":{"n":{"g":0}}},"e":{"l":{"e":{"n":{"a":{" ":{"G":{"o":{"m":{"e":{"z":0}}}}}}}}},"v":{"y":{"n":{" ":{"S":{"t":{"r":{"e":{"e":{"t":{"e":{"r":0}}}}}}}}}}},"r":{"e":{"b":{"r":{"o":0}},"n":{"a":{" ":{"R":{"y":{"d":{"e":{"r":0}}}}}}}},"g":{"i":{"o":{" ":{"D":{"a":{"l":{"m":{"a":0}}}}}}}}},"a":{"n":{" ":{"P":{"a":{"u":{"l":0}}}}}},"b":{"a":{"s":{"t":{"i":{"a":{"n":{" ":{"I":{"n":{"g":{"r":{"o":{"s":{"s":{"o":0}}}}}}}}}}}}}}}},"a":{"r":{"a":{" ":{"B":{"a":{"r":{"e":{"i":{"l":{"l":{"e":{"s":0}}}}}}}}}}},"m":{" ":{"S":{"m":{"i":{"t":{"h":0}}}}},"a":{"n":{"t":{"h":{"a":{" ":{"J":{"a":{"d":{"e":0}}}}}}}}},"p":{"h":{"a":0}}},"g":{"e":{" ":{"T":{"h":{"e":{" ":{"G":{"e":{"m":{"i":{"n":{"i":0}}}}}}}}}}}},"n":{"t":{"a":{"n":{"a":0}}},"d":{"e":{"r":{" ":{"v":{"a":{"n":{" ":{"D":{"o":{"o":{"r":{"n":0}}}}}}}}}}}}," ":{"C":{"i":{"s":{"c":{"o":0}}}}}},"d":{"e":0}},"H":{"I":{"N":{"e":{"e":0}}}},"u":{"b":{" ":{"F":{"o":{"c":{"u":{"s":0}}}}}},"n":{" ":{"K":{"i":{"l":{" ":{"M":{"o":{"o":{"n":0}}}}}}}},"i":{"d":{"h":{"i":{" ":{"C":{"h":{"a":{"u":{"h":{"a":{"n":0}}}}}}}}}}},"r":{"i":{"s":{"e":{" ":{"A":{"v":{"e":{"n":{"u":{"e":0}}}}}}}}}}},"z":{"a":{"n":{"n":{"e":{" ":{"V":{"e":{"g":{"a":0}}}}}}}}},"i":{"c":{"i":{"d":{"e":{" ":{"C":{"o":{"m":{"m":{"a":{"n":{"d":{"o":0}}}}}}}}}}}}}},"o":{"p":{"h":{"i":{"e":{" ":{"E":{"l":{"l":{"i":{"s":{"-":{"B":{"e":{"x":{"t":{"o":{"r":0}}}}}}}}}}}}}}}},"n":{"u":{" ":{"N":{"i":{"g":{"a":{"m":0}}}}}}},"m":{"o":0},"r":{"r":{"i":{"s":{"o":{" ":{"M":{"a":{"r":{"o":{"t":{"o":0}}}}}}}}}}},"h":{"n":0}},"c":{"h":{"o":{"o":{"l":{"b":{"o":{"y":{" ":{"Q":0}}}}}}},"a":{"n":{"d":{"m":{"a":{"u":{"l":0}}}}}}},"o":{"t":{"t":{"y":{" ":{"M":{"c":{"C":{"r":{"e":{"e":{"r":{"y":0}}}}}}}}}}},"o":{"t":{"e":{"r":0}}}},"a":{"n":{"d":{"a":{"l":0}}}}},"w":{"e":{"d":{"i":{"s":{"h":{" ":{"H":{"o":{"u":{"s":{"e":{" ":{"M":{"a":{"f":{"i":{"a":0}}}}}}}}}}}}}}}},"i":{"t":{"c":{"h":{"f":{"o":{"o":{"t":0}}}}}}}},"E":{"K":{"A":{"I":{" ":{"N":{"O":{" ":{"O":{"W":{"A":{"R":{"I":0}}}}}}}}}}}},"k":{"r":{"i":{"l":{"l":{"e":{"x":0}}}}},"i":{"l":{"l":{"e":{"t":0}}},"n":{"d":{"r":{"e":{"d":0}}}}},"y":{" ":{"F":{"e":{"r":{"r":{"e":{"i":{"r":{"a":0}}}}}}}},"l":{"a":{"r":{" ":{"G":{"r":{"e":{"y":0}}}}}}}}},"y":{"s":{"t":{"e":{"m":{" ":{"o":{"f":{" ":{"a":{" ":{"D":{"o":{"w":{"n":0}}}}}}}}}}}}}},"p":{"o":{"r":{"t":{"f":{"r":{"e":{"u":{"n":{"d":{"e":{" ":{"S":{"t":{"i":{"l":{"l":{"e":{"r":0}}}}}}}}}}}}}}}}}},"n":{"o":{"w":{" ":{"P":{"a":{"t":{"r":{"o":{"l":0}}}}}}}}},"l":{"e":{"e":{"p":{"i":{"n":{"g":{" ":{"W":{"i":{"t":{"h":{" ":{"S":{"i":{"r":{"e":{"n":{"s":0}}}}}}}}}}}}}}}}}},"i":{"m":{"p":{"l":{"e":{" ":{"P":{"l":{"a":{"n":0}}}}}}},"o":{"n":{" ":{"&":{" ":{"G":{"a":{"r":{"f":{"u":{"n":{"k":{"e":{"l":0}}}}}}}}}}}}}},"g":{"u":{"r":{" ":{"R":{"ó":{"s":0}}}}}},"l":{"v":{"e":{"r":{"s":{"u":{"n":{" ":{"P":{"i":{"c":{"k":{"u":{"p":{"s":0}}}}}}}}}}}}}},"d":{"o":0,"e":{"w":{"a":{"l":{"k":{" ":{"P":{"r":{"o":{"p":{"h":{"e":{"t":{"s":0}}}}}}}}}}}}},"n":{"e":{"y":{" ":{"S":{"a":{"m":{"s":{"o":{"n":0}}}}}}}}}},"s":{"t":{"a":{"r":0}}},"a":0},"K":{"E":{"4":{"8":0}}},"P":{"Y":{"A":{"I":{"R":0}}},"I":{"C":{"Y":{" ":{"C":{"H":{"O":{"C":{"O":{"L":{"A":{"T":{"E":0}}}}}}}}}}}}}},"J":{"a":{"s":{"o":{"n":{" ":{"D":{"e":{"r":{"ü":{"l":{"o":0}}}}},"A":{"l":{"d":{"e":{"a":{"n":0}}}}},"M":{"r":{"a":{"z":0}}}}}}},"m":{"e":{"s":{" ":{"B":{"l":{"u":{"n":{"t":0}},"a":{"k":{"e":0}}}},"A":{"r":{"t":{"h":{"u":{"r":0}}}}},"V":{"i":{"n":{"c":{"e":{"n":{"t":{" ":{"M":{"c":{"M":{"o":{"r":{"r":{"o":{"w":0}}}}}}}}}}}}}}}}}}},"y":{"-":{"Z":0}},"k":{"e":{" ":{"B":{"u":{"g":{"g":0}}},"M":{"i":{"l":{"l":{"e":{"r":0}}}}}}}},"c":{"k":{" ":{"J":{"o":{"h":{"n":{"s":{"o":{"n":0}}}}}}}}},"g":{"j":{"i":{"t":{" ":{"S":{"i":{"n":{"g":{"h":0}}}}}}}}},"n":{"e":{"l":{"l":{"e":{" ":{"M":{"o":{"n":{"á":{"e":0}}}}}}}}}},"b":{"b":{"e":{"r":{"w":{"o":{"c":{"k":{"y":0}}}}}}}},"z":{"z":{"a":{"n":{"o":{"v":{"a":0}}}}}},"v":{"e":{"d":{" ":{"A":{"l":{"i":0}}}}}}},"u":{"s":{"t":{"i":{"n":{" ":{"T":{"i":{"m":{"b":{"e":{"r":{"l":{"a":{"k":{"e":0}}}}}}}}},"B":{"i":{"e":{"b":{"e":{"r":0}}}}},"M":{"o":{"o":{"r":{"e":0}}}}}}}}},"a":{"n":{"e":{"s":0}," ":{"M":{"a":{"g":{"a":{"n":0}}}}}}},"i":{"c":{"y":{" ":{"J":0}}}},"l":{"i":{"e":{"n":{" ":{"D":{"o":{"r":{"é":0}}}}}},"o":{"n":{" ":{"A":{"l":{"v":{"a":{"r":{"e":{"z":{" ":{"y":{" ":{"S":{"u":{" ":{"N":{"o":{"r":{"t":{"e":{"n":{"o":{" ":{"B":{"a":{"n":{"d":{"a":0}}}}}}}}}}}}}}}}}}}}}}}}}}}}}}},"o":{"h":{"n":{" ":{"N":{"e":{"w":{"m":{"a":{"n":0}}}}},"L":{"e":{"g":{"e":{"n":{"d":0}}},"n":{"n":{"o":{"n":0}}}}},"M":{"a":{"y":{"e":{"r":0}}}},"D":{"e":{"n":{"v":{"e":{"r":0}}}}}},"n":{"y":{" ":{"C":{"a":{"s":{"h":0}}}}}}}},"r":{"g":{"e":{" ":{"&":{" ":{"M":{"a":{"t":{"e":{"u":{"s":0}}}}}}}}}}},"y":{" ":{"D":{"i":{"v":{"i":{"s":{"i":{"o":{"n":0}}}}}}}}},"n":{" ":{"P":{"a":{"r":{"d":{"i":0}}}}}},"v":{"a":{"n":{"o":{"t":{"t":{"i":0}}}}}},"J":{"o":0},"u":{"r":{"n":{"e":{"y":0}}}},"s":{"h":{" ":{"G":{"a":{"d":0}}}}},"e":{" ":{"N":{"i":{"c":{"h":{"o":{"l":{"s":0}}}}}}}}},"e":{"n":{"n":{"i":{"f":{"e":{"r":{" ":{"L":{"o":{"p":{"e":{"z":0}}}},"R":{"o":{"s":{"t":{"o":{"c":{"k":0}}}}}},"H":{"u":{"d":{"s":{"o":{"n":0}}}}}}}}}," ":{"R":{"i":{"v":{"e":{"r":{"a":0}}}}},"V":{"a":{"r":{"t":{"i":{"a":{"i":{"n":{"e":{"n":0}}}}}}}}}}}}},"s":{"s":{"e":{" ":{"&":{" ":{"J":{"o":{"y":0}}}}}},"i":{"e":{" ":{"J":0}},"c":{"a":{" ":{"M":{"a":{"u":{"b":{"o":{"y":0}}}}},"S":{"u":{"t":{"t":{"a":0}}}}}}}}}},"f":{"f":{" ":{"B":{"e":{"r":{"n":{"a":{"t":0}}}}}}}},"r":{"r":{"o":{"d":{" ":{"N":{"i":{"e":{"m":{"a":{"n":{"n":0}}}}}}}}}}}},".":{" ":{"C":{"o":{"l":{"e":0}}}}},"H":{"e":{"n":{"e":{" ":{"A":{"i":{"k":{"o":0}}}}}}}}," ":{"B":{"a":{"l":{"v":{"i":{"n":0}}}}}},"i":{"m":{"i":{" ":{"H":{"e":{"n":{"d":{"r":{"i":{"x":0}}}}}}}}," ":{"J":{"o":{"n":{"e":{"s":0}}}}}}},"U":{"N":{"I":{"E":{"L":0}}}}},"C":{"a":{"l":{"v":{"i":{"n":{" ":{"H":{"a":{"r":{"r":{"i":{"s":0}}}}}}}}},"i":{"b":{"r":{"e":{" ":{"5":{"0":0}}}},"a":{"n":0}}}},"p":{"i":{"t":{"a":{"l":{" ":{"C":{"i":{"t":{"i":{"e":{"s":0}}}}}}}}}}},"g":{"e":{" ":{"t":{"h":{"e":{" ":{"E":{"l":{"e":{"p":{"h":{"a":{"n":{"t":0}}}}}}}}}}}}}},"s":{"h":{" ":{"C":{"a":{"s":{"h":0}}}}},"t":{"i":{"n":{"g":{" ":{"C":{"r":{"o":{"w":{"n":{"s":0}}}}}}}}}},"s":{"a":{"d":{"e":{"e":{" ":{"P":{"o":{"p":{"e":0}}}}}}}},"e":{"u":{"r":{"s":{" ":{"F":{"l":{"o":{"w":{"t":{"e":{"r":{"s":0}}}}}}}}}}}}},"p":{"e":{"r":0}}},"r":{"l":{"y":{" ":{"R":{"a":{"e":{" ":{"J":{"e":{"p":{"s":{"e":{"n":0}}}}}}}}}}},"o":{"s":{" ":{"V":{"i":{"v":{"e":{"s":0}}}},"B":{"a":{"u":{"t":{"e":0}}}}}}}},"o":{"l":{"e":{" ":{"K":{"i":{"n":{"g":0}}}}}}},"t":{"e":{"l":{" ":{"D":{"e":{" ":{"S":{"a":{"n":{"t":{"a":0}}}}}}}}}}},"p":{"a":{"r":{"k":{" ":{"N":{"o":{"r":{"t":{"h":0}}}}}}}}}},"t":{"s":{" ":{"o":{"n":{" ":{"T":{"r":{"e":{"e":{"s":0}}}}}}}}}," ":{"S":{"t":{"e":{"v":{"e":{"n":{"s":0}}}}}}}},"k":{"e":{"d":{" ":{"U":{"p":0}}}}},"m":{"r":{"y":{"n":0}}}},"l":{"e":{"a":{"n":{" ":{"B":{"a":{"n":{"d":{"i":{"t":0}}}}}}}}},"a":{"u":{"d":{"i":{"a":{" ":{"L":{"e":{"i":{"t":{"t":{"e":0}}}}}}}}}},"r":{"i":{"S":0}}}},"h":{"r":{"i":{"s":{" ":{"B":{"r":{"o":{"w":{"n":0}}}},"M":{"a":{"l":{"i":{"n":{"c":{"h":{"a":{"k":0}}}}}}}},"L":{"a":{"k":{"e":0}}}},"t":{"i":{"n":{"a":{" ":{"A":{"g":{"u":{"i":{"l":{"e":{"r":{"a":0}}}}}}},"P":{"e":{"r":{"r":{"i":0}}}}}}}},"o":{"p":{"h":{"e":{"r":0}}}}}}}},"i":{"l":{"d":{"i":{"s":{"h":{" ":{"G":{"a":{"m":{"b":{"i":{"n":{"o":0}}}}}}}}}}}},"t":{"ã":{"o":{"z":{"i":{"n":{"h":{"o":{" ":{"&":{" ":{"X":{"o":{"r":{"o":{"r":{"ó":0}}}}}}}}}}}}}}}},"e":{"f":{" ":{"K":{"e":{"e":{"f":0}}}}}}},"a":{"s":{"e":{" ":{"&":{" ":{"S":{"t":{"a":{"t":{"u":{"s":0}}}}}}}}}},"r":{"l":{"i":{" ":{"X":{"C":{"X":0}}}}}}},"e":{"r":0,"t":{" ":{"F":{"a":{"k":{"e":{"r":0}}}}}},"e":{"k":0}},"l":{"ö":{"e":{" ":{"H":{"o":{"w":{"l":0}}}}}}},"o":{"i":{"r":{" ":{"o":{"f":{" ":{"Y":{"o":{"u":{"n":{"g":{" ":{"B":{"e":{"l":{"i":{"e":{"v":{"e":{"r":{"s":0}}}}}}}}}}}}}}}}}}}}},"u":{"c":{"k":{"i":{"e":0}}}}},"H":{"V":{"R":{"C":{"H":{"E":{"S":0}}}}}},"o":{"l":{"d":{"p":{"l":{"a":{"y":0}}}},"e":{" ":{"S":{"w":{"i":{"n":{"d":{"e":{"l":{"l":0}}}}}}}}},"b":{"i":{"e":{" ":{"C":{"a":{"i":{"l":{"l":{"a":{"t":0}}}}}}}}}}},"m":{"b":{"i":{"c":{"h":{"r":{"i":{"s":{"t":0}}}}}}}}},"é":{"l":{"i":{"n":{"e":{" ":{"D":{"i":{"o":{"n":0}}}}}}}}},"i":{"a":{"r":{"a":0}}},"r":{"i":{"s":{"t":{"i":{"a":{"n":{"o":{" ":{"A":{"r":{"a":{"ú":{"j":{"o":0}}}}}}}}}}}," ":{"C":{"a":{"b":0}}}}},"o":0,"y":{"s":{"t":{"a":{"l":{" ":{"C":{"a":{"s":{"t":{"l":{"e":{"s":0}}}}}}}}}}}}},"n":{"b":{"l":{"u":{"e":0}}}},"œ":{"u":{"r":{" ":{"D":{"e":{" ":{"P":{"i":{"r":{"a":{"t":{"e":0}}}}}}}}}}}},"P":{"M":{" ":{"2":{"2":0}}}}},"R":{"i":{"h":{"a":{"n":{"n":{"a":0}}}},"c":{"k":{"y":{" ":{"M":{"a":{"r":{"t":{"i":{"n":0}}}}}}}," ":{"R":{"o":{"s":{"s":0}}}}},"a":{"r":{"d":{"o":{" ":{"A":{"r":{"j":{"o":{"n":{"a":0}}}}},"M":{"o":{"n":{"t":{"a":{"n":{"e":{"r":0}}}}}}}}}}}},"h":{"a":{"r":{"d":{" ":{"C":{"l":{"a":{"y":{"d":{"e":{"r":{"m":{"a":{"n":0}}}}}}}}}}}}}}},"z":{"z":{"l":{"e":{" ":{"K":{"i":{"c":{"k":{"s":0}}}}}}}}}},"o":{"b":{"i":{"n":{" ":{"T":{"h":{"i":{"c":{"k":{"e":0}}}}},"S":{"c":{"h":{"u":{"l":{"z":0}}}}}}}},"b":{"i":{"e":{" ":{"W":{"i":{"l":{"l":{"i":{"a":{"m":{"s":0}}}}}}}}}}},"e":{"r":{"t":{"o":{" ":{"C":{"a":{"r":{"l":{"o":{"s":0}}}}},"T":{"a":{"p":{"i":{"a":0}}}}}}}}}},"m":{"e":{"o":{" ":{"S":{"a":{"n":{"t":{"o":{"s":0}}}}}}}}},"s":{"a":{"n":{"n":{"e":{" ":{"C":{"a":{"s":{"h":0}}}}}}},"r":{"i":{"o":0}}}},"d":{" ":{"S":{"t":{"e":{"w":{"a":{"r":{"t":0}}}}}}}},"x":{"e":{"t":{"t":{"e":0}}}}},"u":{"d":{"i":{"m":{"e":{"n":{"t":{"a":{"l":0}}}}}}},"s":{"s":{"i":{"a":{"n":{" ":{"R":{"e":{"d":0}}}}}}}}},"a":{"d":{"i":{"o":{"h":{"e":{"a":{"d":0}}}}}},"s":{"c":{"a":{"l":{" ":{"F":{"l":{"a":{"t":{"t":{"s":0}}}}}}}}},"m":{"u":{"s":{" ":{"S":{"e":{"e":{"b":{"a":{"c":{"h":0}}}}}}}}}}},"n":{"d":{"y":{" ":{"H":{"o":{"u":{"s":{"e":{"r":0}}}}}}}}},"g":{"e":{" ":{"A":{"g":{"a":{"i":{"n":{"s":{"t":{" ":{"t":{"h":{"e":{" ":{"M":{"a":{"c":{"h":{"i":{"n":{"e":0}}}}}}}}}}}}}}}}}}}}},"m":{"m":{"s":{"t":{"e":{"i":{"n":0}}}}}},"v":{"i":{" ":{"S":{"h":{"a":{"n":{"k":{"a":{"r":0}}}}}}}}},"h":{"a":{"t":{" ":{"F":{"a":{"t":{"e":{"h":{" ":{"A":{"l":{"i":{" ":{"K":{"h":{"a":{"n":0}}}}}}}}}}}}}}}}}},"e":{"d":{" ":{"H":{"o":{"t":{" ":{"C":{"h":{"i":{"l":{"i":{" ":{"P":{"e":{"p":{"p":{"e":{"r":{"s":0}}}}}}}},"l":{"i":{" ":{"P":{"i":{"p":{"e":{"r":{"s":0}}}}}}}}}}}}}}}},"F":{"o":{"o":0}}}},"v":{"o":{"l":{"v":{"e":{"r":{"h":{"e":{"l":{"d":0}}}}}}}}},"i":{"k":0},"b":{"e":{"c":{"c":{"a":{" ":{"F":{"e":{"r":{"g":{"u":{"s":{"o":{"n":0}}}}}}}}}}}}},"n":{"a":{"t":{"o":{" ":{"Z":{"e":{"r":{"o":0}}}}}}}}},".":{" ":{"K":{"e":{"l":{"l":{"y":0}}}}},"E":{".":{"M":{".":0}}}},"í":{"o":{" ":{"R":{"o":{"m":{"a":0}}}}}},"A":{"D":{"W":{"I":{"M":{"P":{"S":0}}}}}},"ö":{"y":{"k":{"s":{"o":{"p":{"p":0}}}}}}},"Z":{"e":{"d":{"d":0},"n":{"d":{"a":{"y":{"a":0}}}},"z":{"é":{" ":{"D":{"i":{" ":{"C":{"a":{"m":{"a":{"r":{"g":{"o":{" ":{"&":{" ":{"L":{"u":{"c":{"i":{"a":{"n":{"o":0}}}}}}}}}}}}}}}}}}}}}},"r":{"o":{" ":{"A":{"s":{"s":{"o":{"l":{"u":{"t":{"o":0}}}}}}}}}}},"a":{"c":{" ":{"B":{"r":{"o":{"w":{"n":{" ":{"B":{"a":{"n":{"d":0}}}}}}}}}}},"r":{"a":{" ":{"L":{"a":{"r":{"s":{"s":{"o":{"n":0}}}}}}}}}},"o":{"é":0},"u":{"c":{"c":{"h":{"e":{"r":{"o":0}}}}}}},"U":{"2":0,"s":{"h":{"e":{"r":0}}},"V":{"E":{"R":{"w":{"o":{"r":{"l":{"d":0}}}}}}},"d":{"i":{"t":{" ":{"N":{"a":{"r":{"a":{"y":{"a":{"n":0}}}}}}}}}},"N":{"I":{"S":{"O":{"N":{" ":{"S":{"Q":{"U":{"A":{"R":{"E":{" ":{"G":{"A":{"R":{"D":{"E":{"N":0}}}}}}}}}}}}}}}}}}},"T":{"a":{"y":{"l":{"o":{"r":{" ":{"S":{"w":{"i":{"f":{"t":0}}}},"H":{"e":{"n":{"d":{"e":{"r":{"s":{"o":{"n":0}}}}}}}}}}}}},"l":{"$":0,"i":{"b":{" ":{"K":{"w":{"e":{"l":{"i":0}}}}}}}},"m":{"a":{"r":{" ":{"B":{"r":{"a":{"x":{"t":{"o":{"n":0}}}}}}}}},"e":{" ":{"I":{"m":{"p":{"a":{"l":{"a":0}}}}}},"l":{"a":{" ":{"M":{"a":{"n":{"n":0}}}}}}}},"i":{"o":{" ":{"C":{"r":{"u":{"z":0}}}}}}},"h":{"e":{" ":{"1":{"9":{"7":{"5":0}}},"V":{"e":{"r":{"v":{"e":0}}}},"B":{"e":{"a":{"t":{"l":{"e":{"s":0}}}}},"l":{"a":{"c":{"k":{" ":{"K":{"e":{"y":{"s":0}}},"E":{"y":{"e":{"d":{" ":{"P":{"e":{"a":{"s":0}}}}}}}}}}}}},"a":{"n":{"d":{" ":{"P":{"e":{"r":{"r":{"y":0}}}}}}}}},"X":{"X":0},"N":{"e":{"i":{"g":{"h":{"b":{"o":{"u":{"r":{"h":{"o":{"o":{"d":0}}}}}}}}}}},"a":{"t":{"i":{"o":{"n":{"a":{"l":0}}}}},"k":{"e":{"d":{" ":{"A":{"n":{"d":{" ":{"F":{"a":{"m":{"o":{"u":{"s":0}}}}}}}}}}}}}},"o":{"t":{"o":{"r":{"i":{"o":{"u":{"s":{" ":{"B":{".":{"I":{".":{"G":{".":0}}}}}}}}}}}},"w":{"i":{"s":{"t":0}}}}}},"L":{"u":{"m":{"i":{"n":{"e":{"e":{"r":{"s":0}}}}}}}},"F":{"r":{"a":{"y":0,"t":{"e":{"l":{"l":{"i":{"s":0}}}}}}}},"K":{"i":{"l":{"l":{"e":{"r":{"s":0}}}}},"o":{"o":{"k":{"s":0}}}},"R":{"o":{"l":{"l":{"i":{"n":{"g":{" ":{"S":{"t":{"o":{"n":{"e":{"s":0}}}}}}}}}}}}},"G":{"l":{"i":{"t":{"c":{"h":{" ":{"M":{"o":{"b":0}}}}}}}}},"J":{"o":{"h":{"n":{" ":{"B":{"u":{"t":{"l":{"e":{"r":{" ":{"T":{"r":{"i":{"o":0}}}}}}}}}}}}}},"e":{"z":{"a":{"b":{"e":{"l":{"s":0}}}}}}},"S":{"m":{"i":{"t":{"h":{"s":0}}},"a":{"s":{"h":{"i":{"n":{"g":{" ":{"P":{"u":{"m":{"p":{"k":{"i":{"n":{"s":0}}}}}}}}}}}}}}},"c":{"r":{"i":{"p":{"t":0}}}},"t":{"r":{"o":{"k":{"e":{"s":0}}},"y":{"p":{"e":{"s":0}}}}},"h":{"i":{"n":{"s":0}}}},"W":{"h":{"i":{"t":{"e":{" ":{"S":{"t":{"r":{"i":{"p":{"e":{"s":0}}}}}}}}}},"o":0},"a":{"n":{"t":{"e":{"d":0}}}},"e":{"e":{"k":{"n":{"d":0}}}},"o":{"m":{"b":{"a":{"t":{"s":0}}}}}},"P":{"i":{"a":{"n":{"o":{" ":{"G":{"u":{"y":{"s":0}}}}}}}},"r":{"e":{"t":{"t":{"y":{" ":{"R":{"e":{"c":{"k":{"l":{"e":{"s":{"s":0}}}}}}}}}}},"a":{"t":{"u":{"r":{"e":{"s":0}}}}},"s":{"e":{"t":{"s":0}}}}},"o":{"l":{"i":{"c":{"e":0}}}}},"D":{"o":{"o":{"r":{"s":0}}},"e":{"a":{"d":{" ":{"W":{"e":{"a":{"t":{"h":{"e":{"r":0}}}}}}}}}}},"C":{"u":{"r":{"e":0}},"r":{"a":{"n":{"b":{"e":{"r":{"r":{"i":{"e":{"s":0}}}}}}}}},"h":{"a":{"i":{"n":{"s":{"m":{"o":{"k":{"e":{"r":{"s":0}}}}}}}}}}},"A":{"l":{"l":{"m":{"a":{"n":{" ":{"B":{"r":{"o":{"t":{"h":{"e":{"r":{"s":{" ":{"B":{"a":{"n":{"d":0}}}}}}}}}}}}}}}}}},"s":{"t":{"o":{"n":{" ":{"S":{"h":{"u":{"f":{"f":{"l":{"e":0}}}}}}}}}}},"i":{"r":{"b":{"o":{"r":{"n":{"e":{" ":{"T":{"o":{"x":{"i":{"c":{" ":{"E":{"v":{"e":{"n":{"t":0}}}}}}}}}}}}}}}}}},"m":{"i":{"t":{"y":{" ":{"A":{"f":{"f":{"l":{"i":{"c":{"t":{"i":{"o":{"n":0}}}}}}}}}}}}}},"f":{"t":{"e":{"r":{"s":0}}}}},"O":{"f":{"f":{"s":{"p":{"r":{"i":{"n":{"g":0}}}}}}}}}},"a":{"l":{"i":{"a":0}},"e":{"m":{"e":{" ":{"&":{" ":{"T":{"h":{"i":{"a":{"g":{"o":0}}}}}}}}}}}},"o":{"m":{"a":{"s":{" ":{"R":{"h":{"e":{"t":{"t":0}}}}}}},"p":{"s":{"o":{"n":{" ":{"S":{"q":{"u":{"a":{"r":{"e":0}}}}}}}}}}}},"i":{"a":{"g":{"u":{"i":{"n":{"h":{"o":0}}}}}}}},"i":{"ë":{"s":{"t":{"o":0}}},"n":{"i":{"e":{" ":{"T":{"e":{"m":{"p":{"a":{"h":0}}}}}}}},"a":{" ":{"T":{"u":{"r":{"n":{"e":{"r":0}}}}}}}},"m":{" ":{"M":{"c":{"G":{"r":{"a":{"w":0}}}}},"B":{"e":{"n":{"d":{"z":{"k":{"o":0}}}}}}},"b":{"a":{"l":{"a":{"n":{"d":0}}}}}},"r":{"o":{"m":{"a":{"n":{"c":{"i":{"n":{"o":0}}}}}}}}},"o":{"m":{" ":{"O":{"d":{"e":{"l":{"l":0}}}}}},"n":{"i":{" ":{"B":{"r":{"a":{"x":{"t":{"o":{"n":0}}}}}}}}},"d":{"d":{" ":{"T":{"e":{"r":{"j":{"e":0}}}}}}},"b":{"y":{" ":{"K":{"e":{"i":{"t":{"h":0}}}}}}}},"r":{"e":{"y":{" ":{"S":{"o":{"n":{"g":{"z":0}}}}}}},"a":{"n":{"s":{"a":{"t":{"l":{"a":{"n":{"t":{"i":{"c":0}}}}}}}}},"v":{"i":{"s":0}},"c":{"y":{" ":{"C":{"h":{"a":{"p":{"m":{"a":{"n":0}}}}}}}}}}},"-":{"P":{"a":{"i":{"n":0}}}},"y":{"g":{"a":0},"r":{"e":{"s":{"e":0}}},"c":{"h":{"o":0}}},"w":{"o":{" ":{"D":{"o":{"o":{"r":{" ":{"C":{"i":{"n":{"e":{"m":{"a":{" ":{"C":{"l":{"u":{"b":0}}}}}}}}}}}}}}},"F":{"i":{"n":{"g":{"e":{"r":{"z":0}}}}}}}},"e":{"n":{"t":{"y":{" ":{"O":{"n":{"e":{" ":{"P":{"i":{"l":{"o":{"t":{"s":0}}}}}}}}}}}}}}},"e":{"m":{"p":{"l":{"e":{"s":0}}}},"g":{"a":{"n":{" ":{"a":{"n":{"d":{" ":{"S":{"a":{"r":{"a":0}}}}}}}}}}},"x":{"a":{"s":0}}},".":{"I":{".":0},"O":{".":{"P":0}}},"u":{"r":{"m":{"a":{" ":{"d":{"o":{" ":{"P":{"a":{"g":{"o":{"d":{"e":0}}}}}}}}}}}}},"H":{"E":{" ":{"S":{"E":{"C":{"O":{"N":{"D":{" ":{"f":{"r":{"o":{"m":{" ":{"E":{"X":{"I":{"L":{"E":0}}}}}}}}}}}}}}}}}}}},"w":{"i":{"l":{"l":{".":{"i":{".":{"a":{"m":0}}}}}}}},"F":{"a":{"l":{"l":{" ":{"O":{"u":{"t":{" ":{"B":{"o":{"y":0}}}}}}}},"g":{"u":{"n":{"i":{" ":{"P":{"a":{"t":{"h":{"a":{"k":0}}}}}}}}}}},"t":{"b":{"o":{"y":{" ":{"S":{"l":{"i":{"m":0}}}}}}}},"u":{"v":{"e":0},"l":{" ":{"&":{" ":{"W":{"a":{"d":{" ":{"A":{"d":{" ":{"v":{"s":{".":{" ":{"P":{"n":{"a":{"u":0}}}}}}}}}}}}}}}}}}},"m":{"i":{"l":{"y":{" ":{"o":{"f":{" ":{"t":{"h":{"e":{" ":{"Y":{"e":{"a":{"r":0}}}}}}}}}}}}}}},"b":{"a":{"b":{"y":0}}},"r":{"i":{"d":{" ":{"B":{"a":{"n":{"g":0}}}}}}}},"l":{"o":{" ":{"R":{"i":{"d":{"a":0}}}},"r":{"i":{"d":{"a":{" ":{"G":{"e":{"o":{"r":{"g":{"i":{"a":{" ":{"L":{"i":{"n":{"e":0}}}}}}}}}}}}}}},"e":{"n":{"c":{"e":{" ":{"+":{" ":{"T":{"h":{"e":{" ":{"M":{"a":{"c":{"h":{"i":{"n":{"e":0}}}}}}}}}}}}}}}}}}},"e":{"e":{"t":{"w":{"o":{"o":{"d":{" ":{"M":{"a":{"c":0}}}}}}}}}},"u":{"m":{"e":0}},"y":{" ":{"P":{"r":{"o":{"j":{"e":{"c":{"t":0}}}}}}}},"i":{"g":{"h":{"t":{" ":{"F":{"a":{"c":{"i":{"l":{"i":{"t":{"i":{"e":{"s":0}}}}}}}}}}}}}},"a":{"t":{"b":{"u":{"s":{"h":{" ":{"Z":{"o":{"m":{"b":{"i":{"e":{"s":0}}}}}}}}}}}}}},"o":{"s":{"t":{"e":{"r":{" ":{"t":{"h":{"e":{" ":{"P":{"e":{"o":{"p":{"l":{"e":0}}}}}}}}}}}}}},"o":{" ":{"F":{"i":{"g":{"h":{"t":{"e":{"r":{"s":0}}}}}}}}},"a":{"l":{"s":0}},"x":{"e":{"s":0}}},"e":{"r":{"g":{"i":{"e":0}},"n":{"a":{"n":{"d":{"o":{" ":{"&":{" ":{"S":{"o":{"r":{"o":{"c":{"a":{"b":{"a":0}}}}}}}}}}}}}}}},"t":{"t":{"e":{"s":{" ":{"B":{"r":{"o":{"t":0}}}}}}}},"d":{"d":{"e":{" ":{"L":{"e":{" ":{"G":{"r":{"a":{"n":{"d":0}}}}}}}}}},"e":{"z":0}},"a":{"r":{",":{" ":{"a":{"n":{"d":{" ":{"L":{"o":{"a":{"t":{"h":{"i":{"n":{"g":{" ":{"i":{"n":{" ":{"L":{"a":{"s":{" ":{"V":{"e":{"g":{"a":{"s":0}}}}}}}}}}}}}}}}}}}}}}}}}}}}},"r":{"a":{"n":{"z":{" ":{"F":{"e":{"r":{"d":{"i":{"n":{"a":{"n":{"d":0}}}}}}}}}},"k":{" ":{"O":{"c":{"e":{"a":{"n":0}}}},"S":{"i":{"n":{"a":{"t":{"r":{"a":0}}}}}}},"i":{"e":{" ":{"B":{"a":{"l":{"l":{"a":{"r":{"d":0}}}}}}}}}},"c":{"e":{"s":{"c":{"a":{" ":{"B":{"a":{"t":{"t":{"i":{"s":{"t":{"e":{"l":{"l":{"i":0}}}}}}}}}}}}}}}}}},"e":{"i":{".":{"W":{"i":{"l":{"d":0}}}}},"n":{"c":{"h":{" ":{"M":{"o":{"n":{"t":{"a":{"n":{"a":0}}}}}}}}}}}},"u":{"s":{"e":{" ":{"O":{"D":{"G":0}}}}},"t":{"u":{"r":{"e":0}}}},"i":{"t":{"z":{" ":{"&":{" ":{"T":{"h":{"e":{" ":{"T":{"a":{"n":{"t":{"r":{"u":{"m":{"s":0}}}}}}}}}}}}}}}},"v":{"e":{" ":{"F":{"i":{"n":{"g":{"e":{"r":{" ":{"D":{"e":{"a":{"t":{"h":{" ":{"P":{"u":{"n":{"c":{"h":0}}}}}}}}}}}}}}}}}}}},"d":{"e":{"l":{" ":{"R":{"u":{"e":{"d":{"a":0}}}}}}}},"f":{"t":{"h":{" ":{"H":{"a":{"r":{"m":{"o":{"n":{"y":0}}}}}}}}}},"u":{"k":0}},".":{"T":{".":{" ":{"I":{"s":{"l":{"a":{"n":{"d":0}}}}}}}}}},"H":{"a":{"i":{"m":0},"r":{"d":{"w":{"e":{"l":{"l":0}}}}},"v":{"a":{"n":{"a":{" ":{"B":{"r":{"o":{"w":{"n":0}}}}}}}}},"l":{"f":{" ":{"M":{"o":{"o":{"n":{" ":{"R":{"u":{"n":0}}}}}}}}}}},"o":{"w":{"a":{"r":{"d":{" ":{"S":{"h":{"o":{"r":{"e":0}}}}}}}}},"z":{"i":{"e":{"r":0}}}},"e":{"l":{"e":{"n":{"e":{" ":{"F":{"i":{"s":{"c":{"h":{"e":{"r":0}}}}}}}}}},"l":{"o":{" ":{"S":{"l":{"e":{"e":{"p":{"w":{"a":{"l":{"k":{"e":{"r":{"s":0}}}}}}}}}}}}}}},"d":{"l":{"e":{"y":0}}},"n":{"r":{"i":{"q":{"u":{"e":{" ":{"&":{" ":{"J":{"u":{"l":{"i":{"a":{"n":{"o":0}}}}}}}}}}}}}}},"z":{"e":{"k":{"i":{"a":{"h":{" ":{"W":{"a":{"l":{"k":{"e":{"r":0}}}}}}}}}}}}},"u":{"n":{"t":{"e":{"r":{" ":{"H":{"a":{"y":{"e":{"s":0}}}}}}}}}},"i":{"l":{"l":{"s":{"o":{"n":{"g":{" ":{"U":{"n":{"i":{"t":{"e":{"d":0}}}}}}}}}},"t":{"o":{"p":{" ":{"H":{"o":{"o":{"d":{"s":0}}}}}}}}}},"m":{"e":{"s":{"h":{" ":{"R":{"e":{"s":{"h":{"a":{"m":{"m":{"i":{"y":{"a":0}}}}}}}}}}}}}}},"K":{"T":{"4":{"8":0}}}},"W":{"a":{"r":{"p":{"a":{"i":{"n":{"t":0}}}}},"l":{"e":0},"s":{"h":{"e":{"d":{" ":{"O":{"u":{"t":0}}}}}}}},"i":{"t":{"h":{"i":{"n":{" ":{"T":{"e":{"m":{"p":{"t":{"a":{"t":{"i":{"o":{"n":0}}}}}}}}}}}}}},"z":{" ":{"K":{"h":{"a":{"l":{"i":{"f":{"a":0}}}}}}}},"l":{"k":{"i":{"n":{"s":{"o":{"n":0}}}}},"l":{" ":{"S":{"p":{"a":{"r":{"k":{"s":0}}}}}},"i":{"e":{" ":{"N":{"e":{"l":{"s":{"o":{"n":0}}}}}}}}}}},"o":{"o":{"d":{"k":{"i":{"d":0}}}}},"h":{"i":{"t":{"n":{"e":{"y":{" ":{"H":{"o":{"u":{"s":{"t":{"o":{"n":0}}}}}}}}}}}},"a":{"t":{" ":{"S":{"o":{" ":{"N":{"o":{"t":0}}}}}}},"m":{"!":0}}},"e":{"e":{"z":{"e":{"r":0}}},"s":{"t":{"l":{"i":{"f":{"e":0}}}}}}},"V":{"a":{"m":{"p":{"i":{"r":{"e":{" ":{"W":{"e":{"e":{"k":{"e":{"n":{"d":0}}}}}}}}}},"s":0}},"n":{"c":{"e":{" ":{"J":{"o":{"y":0}}}}}},"s":{"c":{"o":{" ":{"R":{"o":{"s":{"s":{"i":0}}}}}}}},"l":{"e":{"r":{"i":{"o":{" ":{"S":{"c":{"a":{"n":{"u":0}}}}}}}},"s":{"c":{"a":{" ":{"P":{"o":{"p":{"o":{"z":{"u":{"d":{"a":0}}}}}}}}}}}}}},"o":{"z":{" ":{"D":{"e":{" ":{"M":{"a":{"n":{"d":{"o":0}}}}}}}}},"l":{"b":{"e":{"a":{"t":0}}}}},"i":{"t":{"a":{"a":0}},"c":{"e":{"n":{"t":{"i":{"c":{"o":0}}}},"t":{"o":{"n":{"e":0}}}}}},"e":{"r":{"o":{"n":{"i":{"c":{"a":{" ":{"M":{"a":{"g":{"g":{"i":{"o":0}}}}}}}}}}}}},"I":{"X":{"X":0}}},"Q":{"u":{"e":{"e":{"n":{"$":0,"s":{" ":{"o":{"f":{" ":{"t":{"h":{"e":{" ":{"S":{"t":{"o":{"n":{"e":{" ":{"A":{"g":{"e":0}}}}}}}}}}}}}}}}}}}}}},"Y":{"o":{"u":{" ":{"M":{"e":{" ":{"A":{"t":{" ":{"S":{"i":{"x":0}}}}}}}}},"n":{"g":{" ":{"T":{"h":{"e":{" ":{"G":{"i":{"a":{"n":{"t":0}}}}}}}},"J":{"e":{"e":{"z":{"y":0}}}}}}}}," ":{"Y":{"o":{" ":{"H":{"o":{"n":{"e":{"y":{" ":{"S":{"i":{"n":{"g":{"h":0}}}}}}}}}}}}},"G":{"o":{"t":{"t":{"i":0}}}}}},"l":{"v":{"i":{"s":0}}},"e":{"l":{"l":{"o":{"w":{" ":{"C":{"l":{"a":{"w":0}}}}}}}},"a":{"h":{" ":{"Y":{"e":{"a":{"h":{" ":{"Y":{"e":{"a":{"h":{"s":0}}}}}}}}}}}}},"U":{"K":{"I":0}},"i":{"r":{"u":{"m":{"a":0}}}},"-":{"T":{"I":{"T":{"T":{"Y":0}}}}}},"N":{"i":{"r":{"v":{"a":{"n":{"a":0}}}},"c":{"k":{"i":{" ":{"M":{"i":{"n":{"a":{"j":0}}}}}},"e":{"l":{"b":{"a":{"c":{"k":0}}}}},"y":{" ":{"R":{"o":{"m":{"e":{"r":{"o":0}}}}}}}}},"n":{"e":{" ":{"I":{"n":{"c":{"h":{" ":{"N":{"a":{"i":{"l":{"s":0}}}}}}}}}}},"a":{" ":{"N":{"e":{"s":{"b":{"i":{"t":{"t":0}}}}}},"P":{"e":{"r":{"s":{"s":{"o":{"n":0}}}}}}}}},"g":{"h":{"t":{"w":{"i":{"s":{"h":0}}}}}}},"a":{"u":{"g":{"h":{"t":{"y":{" ":{"B":{"o":{"y":0}}}}}}}},"t":{"a":{"l":{"i":{"a":{" ":{"K":{"i":{"l":{"l":{"s":0}}}}}}}}}},"s":0,"b":{"i":{"h":{"a":0}}}},"e":{"o":{"n":{" ":{"J":{"u":{"n":{"g":{"l":{"e":0}}}}},"T":{"r":{"e":{"e":{"s":0}}}}}}},"i":{"l":{" ":{"Y":{"o":{"u":{"n":{"g":0}}}},"F":{"i":{"n":{"n":0}}}}}},"w":{" ":{"W":{"o":{"r":{"l":{"d":{" ":{"S":{"o":{"u":{"n":{"d":0}}}}}}}}}},"P":{"o":{"l":{"i":{"t":{"i":{"c":{"s":0}}}}}}}},"s":{"b":{"o":{"y":{"s":0}}}}},"n":{"e":{" ":{"M":{"a":{"l":{"o":0}}}}}},"g":{"r":{"a":{"m":{"a":{"r":{"o":0}}}}}},"-":{"Y":{"o":0}},"l":{"l":{"y":{"$":0," ":{"F":{"u":{"r":{"t":{"a":{"d":{"o":0}}}}}}}}}},"u":{"t":{"r":{"a":{"l":{" ":{"M":{"i":{"l":{"k":{" ":{"H":{"o":{"t":{"e":{"l":0}}}}}}}}}}}}}}}},"x":{"Z":{"e":{"r":{"o":0}}}},"E":{"E":{"D":{"T":{"O":{"B":{"R":{"E":{"A":{"T":{"H":{"E":0}}}}}}}}}}},"u":{"s":{"r":{"a":{"t":{" ":{"F":{"a":{"t":{"e":{"h":{" ":{"A":{"l":{"i":{" ":{"K":{"h":{"a":{"n":0}}}}}}}}}}}}}}}}}}},"o":{"e":{"l":{" ":{"S":{"c":{"h":{"a":{"j":{"r":{"i":{"s":0}}}}}}}}}}},"M":{"B":{"4":{"8":0}}}},"G":{"u":{"n":{"s":{" ":{"N":{"'":{" ":{"R":{"o":{"s":{"e":{"s":0}}}}}}}}}},"y":{" ":{"S":{"e":{"b":{"a":{"s":{"t":{"i":{"a":{"n":0}}}}}}}}}},"s":{"t":{"t":{"a":{"v":{"o":{" ":{"L":{"i":{"m":{"a":0}}}}}}}}}},"c":{"c":{"i":{" ":{"M":{"a":{"n":{"e":0}}}}}}}},"i":{"o":{"r":{"g":{"i":{"a":0}}}},"r":{"l":{"'":{"s":{" ":{"D":{"a":{"y":0}}}}}}}},"e":{"o":{"r":{"g":{"e":{" ":{"E":{"z":{"r":{"a":0}}},"M":{"i":{"c":{"h":{"a":{"e":{"l":0}}}}}},"S":{"t":{"r":{"a":{"i":{"t":0}}}}}}}}}},"r":{"a":{"r":{"d":{"o":{" ":{"O":{"r":{"t":{"i":{"z":0}}}}}}}}}},"n":{"t":{"l":{"e":{"m":{"a":{"n":0}}}}}}},"r":{"e":{"e":{"n":{" ":{"D":{"a":{"y":0}}}}}},"a":{"m":{"a":{"t":{"i":{"k":0}}}}},"i":{"m":{"e":{"s":0}}}},"-":{"D":{"r":{"a":{"g":{"o":{"n":0}}}}}},"o":{"r":{"g":{"o":{"n":{" ":{"C":{"i":{"t":{"y":0}}}}}}},"i":{"l":{"l":{"a":{"z":0}}}}},"o":{" ":{"G":{"o":{"o":{" ":{"D":{"o":{"l":{"l":{"s":0}}}}}}}}}},"t":{"y":{"e":0}},"g":{"o":{"l":{" ":{"B":{"o":{"r":{"d":{"e":{"l":{"l":{"o":0}}}}}}}}}}},"l":{"d":{" ":{"P":{"a":{"n":{"d":{"a":0}}}}},"f":{"r":{"a":{"p":{"p":0}}}}}}},"l":{"o":{"r":{"i":{"a":{" ":{"T":{"r":{"e":{"v":{"i":0}}}}}}}}},"e":{"e":{" ":{"C":{"a":{"s":{"t":0}}}}},"n":{"n":{" ":{"M":{"o":{"r":{"r":{"i":{"s":{"o":{"n":0}}}}}}}}}}}},"a":{"r":{"y":{"$":0," ":{"B":{"a":{"r":{"l":{"o":{"w":0}}}}},"C":{"l":{"a":{"r":{"k":{",":{" ":{"J":{"r":{".":0}}}}}}}}}}},"t":{"h":{" ":{"B":{"r":{"o":{"o":{"k":{"s":0}}}}}}}}},"b":{"r":{"i":{"e":{"l":{"l":{"e":{" ":{"A":{"p":{"l":{"i":{"n":0}}}}}}}}}}}}},"O":{"T":{"7":0}},"L":{"A":{"Y":0}}},"비":0,"소":{"녀":{"시":{"대":0}}},"동":{"방":{"신":{"기":0}}},"安":{"室":{"奈":{"美":{"恵":0}}}},"東":{"方":{"神":{"起":0}}},"m":{"i":{"s":{"s":{" ":{"A":0}}},"w":{"a":0}}},"시":{"크":{"릿":0}},"지":{"아":0},"b":{"l":{"i":{"n":{"k":{"-":{"1":{"8":{"2":0}}}}}}}},"西":{"野":{"カ":{"ナ":0}}},"き":{"ゃ":{"り":{"ー":{"ぱ":{"み":{"ゅ":{"ぱ":{"み":{"ゅ":0}}}}}}}}},"コ":{"ブ":{"ク":{"ロ":0}}},"Г":{"р":{"и":{"г":{"о":{"р":{"и":{"й":{" ":{"Л":{"е":{"п":{"с":0}}}}}}}}}}}},"태":{"양":0},"田":{"馥":{"甄":0}},"С":{"е":{"р":{"г":{"е":{"й":{" ":{"Л":{"а":{"з":{"а":{"р":{"е":{"в":0}}}}}}}}}}}}},"휘":{"성":0},"中":{"島":{"美":{"嘉":0}}},"효":{"린":0},"t":{"h":{"e":{" ":{"G":{"a":{"z":{"e":{"t":{"t":{"E":0}}}}}}}}},"o":{"b":{"y":{"M":{"a":{"c":0}}}}}},"加":{"藤":{"ミ":{"リ":{"ヤ":0}}}},"サ":{"カ":{"ナ":{"ク":{"シ":{"ョ":{"ン":0}}}}}},"윤":{"하":0},"f":{"u":{"n":{".":0}},"l":{"o":{"w":{"e":{"r":0}}}},"(":{"x":{")":0}}},"Е":{"в":{"а":{" ":{"П":{"о":{"л":{"ь":{"н":{"а":0}}}}}}}}},"ゆ":{"ず":0},"싸":{"이":0},"가":{"인":0},"五":{"月":{"天":0}},"浜":{"崎":{"あ":{"ゆ":{"み":0}}}},"家":{"入":{"レ":{"オ":0}}},"И":{"р":{"и":{"н":{"а":{" ":{"А":{"л":{"л":{"е":{"г":{"р":{"о":{"в":{"а":0}}}}}}}}}}}}}},"孫":{"燕":{"姿":0}},"А":{"н":{"и":{" ":{"Л":{"о":{"р":{"а":{"к":0}}}}}}}},"걸":{"스":{"데":{"이":0}}},"s":{"a":{"k":{"a":{"n":{"a":{"c":{"t":{"i":{"o":{"n":0}}}}}}}}}},"X":{"a":{"v":{"i":{"e":{"r":{" ":{"N":{"a":{"i":{"d":{"o":{"o":0}}}}}}}}}}}},"애":{"프":{"터":{"스":{"쿨":0}}}},"Н":{"ю":{"ш":{"а":0}}},"Á":{"l":{"e":{"x":{" ":{"U":{"b":{"a":{"g":{"o":0}}}}}}}}},"인":{"피":{"니":{"트":0}}},"汪":{"峰":0},"ス":{"キ":{"マ":{"ス":{"イ":{"ッ":{"チ":0}}}}}},"김":{"동":{"률":0}},"스":{"피":{"카":0}},"関":{"ジ":{"ャ":{"ニ":{"∞":0}}}},"v":{"o":{"X":{"X":{"c":{"l":{"u":{"b":0}}}}}}},"三":{"代":{"目":{" ":{"J":{" ":{"S":{"o":{"u":{"l":{" ":{"B":{"r":{"o":{"t":{"h":{"e":{"r":{"s":0}}}}}}}}}}}}}}}}}},"П":{"и":{"ц":{"ц":{"а":0}}}}}
